qcarchivetesting/__init__.py
qcarchivetesting/data_generator.py
qcarchivetesting/helpers.py
qcarchivetesting/pytest_config.py
qcarchivetesting/test_full_gridoptimization.py
qcarchivetesting/test_full_manybody.py
qcarchivetesting/test_full_neb.py
qcarchivetesting/test_full_optimization.py
qcarchivetesting/test_full_reaction.py
qcarchivetesting/test_full_singlepoint.py
qcarchivetesting/test_full_torsiondrive.py
qcarchivetesting/testing_classes.py
qcarchivetesting/testing_fixtures.py
qcarchivetesting/config_files/gha_fractal_compute.yaml
qcarchivetesting/config_files/gha_fractal_server.yaml
qcarchivetesting/config_files/qcf_basic.yaml
qcarchivetesting/data_generator/clean.py
qcarchivetesting/data_generator/generate_gridoptimization.py
qcarchivetesting/data_generator/generate_manybody.py
qcarchivetesting/data_generator/generate_neb.py
qcarchivetesting/data_generator/generate_optimization.py
qcarchivetesting/data_generator/generate_reaction.py
qcarchivetesting/data_generator/generate_singlepoint.py
qcarchivetesting/data_generator/generate_torsiondrive.py
qcarchivetesting/hash_data/dict_hash_test_data.json.xz
qcarchivetesting/hash_data/generate_random.py
qcarchivetesting/hash_data/gridoptimization_specification_tests.json.xz
qcarchivetesting/hash_data/manybody_specification_tests.json.xz
qcarchivetesting/hash_data/neb_specification_tests.json.xz
qcarchivetesting/hash_data/optimization_specification_tests.json.xz
qcarchivetesting/hash_data/qc_specification_tests.json.xz
qcarchivetesting/hash_data/reaction_specification_tests.json.xz
qcarchivetesting/hash_data/torsiondrive_specification_tests.json.xz
qcarchivetesting/migration_data/empty_v0.15.8.sql_dump
qcarchivetesting/migration_data/qcfractal_config_v0.15.8.yaml
qcarchivetesting/molecule_data/benzene_dimer.json
qcarchivetesting/molecule_data/benzene_dimer.xyz
qcarchivetesting/molecule_data/go_C4H4N2OS.json
qcarchivetesting/molecule_data/go_C6H5N3.json
qcarchivetesting/molecule_data/go_H3NS.json
qcarchivetesting-0.63.dist-info/licenses/LICENSE
qcarchivetesting-0.63.dist-info/METADATA
qcarchivetesting-0.63.dist-info/WHEEL
qcarchivetesting-0.63.dist-info/entry_points.txt
qcarchivetesting-0.63.dist-info/top_level.txt
qcarchivetesting-0.63.dist-info/RECORD
