Metadata-Version: 2.4
Name: qcarchivetesting
Version: 0.63
Summary: A distributed compute and database platform for quantum chemistry.
Author-email: Benjamin Pritchard <qcarchive@molssi.org>
License-Expression: BSD-3-Clause
Project-URL: Homepage, https://github.com/MolSSI/QCFractal
Project-URL: Bug Tracker, https://github.com/MolSSI/QCFractal/issues
Classifier: Programming Language :: Python :: 3
Classifier: Development Status :: 4 - Beta
Classifier: Intended Audience :: Science/Research
Classifier: Operating System :: POSIX :: Linux
Classifier: Operating System :: MacOS
Requires-Python: >=3.10
License-File: LICENSE
Requires-Dist: qcfractal
Requires-Dist: qcengine<0.70a0
Requires-Dist: pytest
Requires-Dist: deepdiff
Dynamic: license-file
